odoo/addons/product_lot_sequence/README.rst
odoo/addons/product_lot_sequence/__init__.py
odoo/addons/product_lot_sequence/__manifest__.py
odoo/addons/product_lot_sequence/i18n/ca.po
odoo/addons/product_lot_sequence/i18n/es.po
odoo/addons/product_lot_sequence/i18n/product_lot_sequence.pot
odoo/addons/product_lot_sequence/models/__init__.py
odoo/addons/product_lot_sequence/models/product.py
odoo/addons/product_lot_sequence/models/stock_production_lot.py
odoo/addons/product_lot_sequence/readme/CONTRIBUTORS.rst
odoo/addons/product_lot_sequence/readme/DESCRIPTION.rst
odoo/addons/product_lot_sequence/readme/USAGE.rst
odoo/addons/product_lot_sequence/static/description/icon.png
odoo/addons/product_lot_sequence/static/description/index.html
odoo/addons/product_lot_sequence/views/product_views.xml
odoo12_addon_product_lot_sequence-12.0.1.0.2.dist-info/METADATA
odoo12_addon_product_lot_sequence-12.0.1.0.2.dist-info/WHEEL
odoo12_addon_product_lot_sequence-12.0.1.0.2.dist-info/top_level.txt
odoo12_addon_product_lot_sequence-12.0.1.0.2.dist-info/RECORD
